LICENSE
MANIFEST.in
setup.cfg
setup.py
fpp/__init__.py
fpp.egg-info/PKG-INFO
fpp.egg-info/SOURCES.txt
fpp.egg-info/dependency_links.txt
fpp.egg-info/requires.txt
fpp.egg-info/top_level.txt